mongrations/ClassType.py
mongrations/__init__.py
mongrations/cache.py
mongrations/cli.py
mongrations/main.py
mongrations/version.py
mongrations/data/reference_file.txt
mongrations-0.0.7.dist-info/METADATA
mongrations-0.0.7.dist-info/WHEEL
mongrations-0.0.7.dist-info/entry_points.txt
mongrations-0.0.7.dist-info/top_level.txt
mongrations-0.0.7.dist-info/RECORD
