Metadata-Version: 2.1
Name: mongrations
Version: 0.0.7
Summary: Migrations tool for Python 3.5+
Home-page: https://github.com/ableinc/mongrations
Author: AbleInc - Jaylen Douglas
Author-email: douglas.jaylen@gmail.com
License: UNKNOWN
Keywords: migrations,python3,automation,database,json,nosql,python,database tool,automation tool,open source,mongodb,mysql,postgres,sql
Platform: UNKNOWN
Classifier: Programming Language :: Python :: 3
Classifier: License :: OSI Approved :: MIT License
Classifier: Operating System :: OS Independent
Requires-Dist: Click (==7.0)
Requires-Dist: motor (==2.0.0)
Requires-Dist: pydotenvs (==0.1.2)
Requires-Dist: pymongo (==3.8.0)
Requires-Dist: PyMySQL (==0.9.3)
Requires-Dist: requests (==2.22.0)
Requires-Dist: psycopg2-binary (==2.8.3)
